hance/__init__.py
hance/hance.py
hance/hance_file.py
hance/version.py
hance/bin/Windows_x64/HanceEngine.dll
hance/models/speech-denoise-11ms.v26.1.hance
hance/models/speech-denoise-21ms.v26.1.hance
hance/models/speech-denoise-32ms-tiny.v26.1.hance
hance/models/speech-denoise-32ms.v26.1.hance
hance/models/speech-denoise-96ms.v26.1.hance
hance/models/speech-denoise-dereverb-11ms.v26.1.hance
hance/models/speech-denoise-dereverb-21ms.v26.1.hance
hance/models/speech-denoise-dereverb-32ms-tiny.v26.1.hance
hance/models/speech-denoise-dereverb-32ms.v26.1.hance
hance/models/speech-denoise-dereverb-96ms.v26.1.hance
hance-26.1.1.dist-info/METADATA
hance-26.1.1.dist-info/WHEEL
hance-26.1.1.dist-info/top_level.txt
hance-26.1.1.dist-info/RECORD
