Metadata-Version: 2.4
Name: hance
Version: 26.1.1
Summary: The Python API to the HANCE engine, which offers realtime audio enhancement.
Home-page: https://hance.ai
Author: HANCE
Author-email: HANCE <mail@hance.ai>
Project-URL: Homepage, https://hance.ai
Keywords: hance,audio enhancement,noise reduction
Classifier: License :: OSI Approved :: MIT License
Classifier: Programming Language :: Python
Classifier: Programming Language :: Python :: 3
Requires-Python: !=2.*,>=3.0
Requires-Dist: setuptools>=41.2.0
Requires-Dist: numpy
Requires-Dist: soundfile
Dynamic: author
Dynamic: home-page
Dynamic: requires-python
